{
  "package": "google.logging.type",
  "syntax": "proto3",
  "root": {
    "nested": {
      "google": {
        "nested": {
          "logging": {
            "nested": {
              "type": {
                "options": {
                  "csharp_namespace": "Google.Cloud.Logging.Type",
                  "go_package": "google.golang.org/genproto/googleapis/logging/type;ltype",
                  "java_multiple_files": true,
                  "java_outer_classname": "LogSeverityProto",
                  "java_package": "com.google.logging.type",
                  "objc_class_prefix": "GLOG",
                  "php_namespace": "Google\\Cloud\\Logging\\Type",
                  "ruby_package": "Google::Cloud::Logging::Type"
                },
                "nested": {
                  "LogSeverity": {
                    "values": {
                      "DEFAULT": 0,
                      "DEBUG": 100,
                      "INFO": 200,
                      "NOTICE": 300,
                      "WARNING": 400,
                      "ERROR": 500,
                      "CRITICAL": 600,
                      "ALERT": 700,
                      "EMERGENCY": 800
                    }
                  }
                }
              }
            }
          }
        }
      }
    }
  }
}